nazca4sdk/__init__.py
nazca4sdk/container.py
nazca4sdk/sdk.py
nazca4sdk/analytics/__brain_connection.py
nazca4sdk/analytics/__init__.py
nazca4sdk/analytics/analytics.py
nazca4sdk/analytics/energy/__init__.py
nazca4sdk/analytics/energy/energy.py
nazca4sdk/analytics/performance_indicators/__init__.py
nazca4sdk/analytics/performance_indicators/indicators.py
nazca4sdk/analytics/performance_indicators/oee_calculations.py
nazca4sdk/analytics/performance_indicators/process_indicators.py
nazca4sdk/analytics/prediction/__init__.py
nazca4sdk/analytics/prediction/forecasting.py
nazca4sdk/analytics/prediction/predictions.py
nazca4sdk/analytics/vibration/__init__.py
nazca4sdk/analytics/vibration/vibration_quality.py
nazca4sdk/datahandling/__init__.py
nazca4sdk/datahandling/data_mod.py
nazca4sdk/datahandling/open_data_client.py
nazca4sdk/datahandling/variable_historical_info.py
nazca4sdk/datahandling/variable_verificator.py
nazca4sdk/datahandling/cache/__init__.py
nazca4sdk/datahandling/cache/cache_storage.py
nazca4sdk/datahandling/cache/key_value.py
nazca4sdk/datahandling/file/__init__.py
nazca4sdk/datahandling/file/file_storage.py
nazca4sdk/datahandling/hotstorage/__init__.py
nazca4sdk/datahandling/hotstorage/helper.py
nazca4sdk/datahandling/hotstorage/query.py
nazca4sdk/datahandling/hotstorage/user_variable_info.py
nazca4sdk/datahandling/hotstorage/user_variable_saver.py
nazca4sdk/datahandling/hotstorage/user_variable_value.py
nazca4sdk/datahandling/hotstorage/user_variables_info_value.py
nazca4sdk/datahandling/hotstorage/user_variables_stats_info.py
nazca4sdk/datahandling/hotstorage/variable_stats.py
nazca4sdk/datahandling/hotstorage/variables_stats_info.py
nazca4sdk/datahandling/hotstorage/model/__init__.py
nazca4sdk/datahandling/hotstorage/model/user_variable.py
nazca4sdk/datahandling/kafka/__init__.py
nazca4sdk/datahandling/kafka/kafka_sender.py
nazca4sdk/datahandling/knowledge/__init__.py
nazca4sdk/datahandling/knowledge/knowledge_data_type.py
nazca40sdk-2.0.0.dist-info/METADATA
nazca40sdk-2.0.0.dist-info/WHEEL
nazca40sdk-2.0.0.dist-info/top_level.txt
nazca40sdk-2.0.0.dist-info/RECORD
