Metadata-Version: 2.1
Name: nazca40sdk
Version: 2.0.0
Summary: Describe your package in one sentence
Home-page: https://github.com/you/your_package
Author: You
Author-email: you@email.com
License: Apache License 2.0
Requires-Dist: numpy
Requires-Dist: pandas
Requires-Dist: dependency-injector
Requires-Dist: mysql-connector-python
Requires-Dist: configparser
Requires-Dist: pydantic
Requires-Dist: clickhouse-driver
Requires-Dist: kafka-python
Requires-Dist: clickhouse-connect
